score/db/__init__.py
score/db/dataloader.py
score/db/dbenum.py
score/db/helpers.py
score/db/pg.py
score/db/pyramid.py
score/db/session.py
score/db/sqlite.py
score.db-0.4.3.dist-info/DESCRIPTION.rst
score.db-0.4.3.dist-info/METADATA
score.db-0.4.3.dist-info/RECORD
score.db-0.4.3.dist-info/WHEEL
score.db-0.4.3.dist-info/metadata.json
score.db-0.4.3.dist-info/top_level.txt
